ytsapi/__init__.py
ytsapi/__main__.py
ytsapi/ytsapi.py
YTSAPI-0.1.1.dist-info/METADATA
YTSAPI-0.1.1.dist-info/WHEEL
YTSAPI-0.1.1.dist-info/entry_points.txt
YTSAPI-0.1.1.dist-info/top_level.txt
YTSAPI-0.1.1.dist-info/RECORD
