Metadata-Version: 2.1
Name: YTSAPI
Version: 0.1.1
Summary: YTSAPI is a python API which allows you to get the transcript/subtitle for a given YouTube video.
Home-page: https://github.com/theabuseproject/YTSAPI
Author: Piyush Raj
Author-email: piyush@linuxmail.org
License: UNKNOWN
Keywords: transcribe-api YTSAPI theabuseproject abuse profanity project youtube-api youtube transcript subtitle youtube-subtitle youtube-transcript api
Platform: UNKNOWN
Classifier: Programming Language :: Python :: 2
Classifier: Programming Language :: Python :: 3
Classifier: License :: OSI Approved :: MIT License
Classifier: Operating System :: OS Independent
Requires-Dist: requests
Requires-Dist: youtube-dl
